[
  {
    "Date": "01012021",
    "Flavor": "Sweet Cream",
    "Position": "5"
  },
  {
    "Date": "01022021",
    "Flavor": "Peppermint",
    "Position": "6"
  },
  {
    "Date": "01032021",
    "Flavor": "Chocolate Malt",
    "Position": "10"
  },
  {
    "Date": "01042021",
    "Flavor": "Salted Caramel",
    "Position": "11"
  },
  {
    "Date": "01052021",
    "Flavor": "Burgundy Cherry",
    "Position": "12"
  },
  {
    "Date": "01062021",
    "Flavor": "Strawberry",
    "Position": "13"
  },
  {
    "Date": "01072021",
    "Flavor": "Jamocha",
    "Position": "14"
  },
  {
    "Date": "01082021",
    "Flavor": "Chocolate Chip Cookie Dough",
    "Position": "15"
  },
  {
    "Date": "01092021",
    "Flavor": "Mint Chocolate Chip",
    "Position": "16"
  },
  {
    "Date": "01102021",
    "Flavor": "Peanut Butter",
    "Position": "20"
  },
  {
    "Date": "01112021",
    "Flavor": "Raspberry",
    "Position": "21"
  },
  {
    "Date": "01122021",
    "Flavor": "Creme Brulee",
    "Position": "22"
  },
  {
    "Date": "01132021",
    "Flavor": "Pistachio",
    "Position": "23"
  },
  {
    "Date": "01142021",
    "Flavor": "Butter Pecan",
    "Position": "24"
  },
  {
    "Date": "01152021",
    "Flavor": "S'mores",
    "Position": "25"
  },
  {
    "Date": "01162021",
    "Flavor": "Cake Batter",
    "Position": "26"
  },
  {
    "Date": "01172021",
    "Flavor": "Mint Chocolate Chip",
    "Position": "30"
  },
  {
    "Date": "01182021",
    "Flavor": "Sweet Cream",
    "Position": "31"
  },
  {
    "Date": "01192021",
    "Flavor": "Blackberry",
    "Position": "32"
  },
  {
    "Date": "01202021",
    "Flavor": "Banana Pudding",
    "Position": "33"
  },
  {
    "Date": "01212021",
    "Flavor": "Peppermint",
    "Position": "34"
  },
  {
    "Date": "01222021",
    "Flavor": "Nutella",
    "Position": "35"
  },
  {
    "Date": "01232021",
    "Flavor": "Chocolate Chip Cookie Dough",
    "Position": "36"
  },
  {
    "Date": "01242021",
    "Flavor": "Burgundy Cherry",
    "Position": "40"
  },
  {
    "Date": "01252021",
    "Flavor": "Chocolate Malt",
    "Position": "41"
  },
  {
    "Date": "01262021",
    "Flavor": "Butter Pecan",
    "Position": "42"
  },
  {
    "Date": "01272021",
    "Flavor": "Salted Caramel",
    "Position": "43"
  },
  {
    "Date": "01282021",
    "Flavor": "Peanut Butter",
    "Position": "44"
  },
  {
    "Date": "01292021",
    "Flavor": "Mint Chocolate Chip",
    "Position": "45"
  },
  {
    "Date": "01302021",
    "Flavor": "Strawberry",
    "Position": "46"
  },
  {
    "Date": "01312021",
    "Flavor": "Jamocha",
    "Position": "50"
  }
]
