[
  {
    "Flavor": "Caramel Apple Crunch",
    "Date": "10262025"
  },
  {
    "Flavor": "Strawberry",
    "Date": "10272025"
  },
  {
    "Flavor": "Cinnamon Bun",
    "Date": "10282025"
  },
  {
    "Flavor": "Pistachio",
    "Date": "10292025"
  },
  {
    "Flavor": "Peanut Butter",
    "Date": "10302025"
  },
  {
    "Flavor": "Pumpkin",
    "Date": "10312025"
  },
  {
    "Flavor": "Sweet Cream",
    "Date": "11012025"
  },
  {
    "Flavor": "Chai Latte Chocolate Chip",
    "Date": "11022025"
  },
  {
    "Flavor": "Jamocha",
    "Date": "11032025"
  },
  {
    "Flavor": "Salted Caramel",
    "Date": "11042025"
  },
  {
    "Flavor": "Mint Chocolate Chip",
    "Date": "11052025"
  },
  {
    "Flavor": "Chocolate Chip Cookie Dough",
    "Date": "11062025"
  },
  {
    "Flavor": "Butter Pecan",
    "Date": "11072025"
  },
  {
    "Flavor": "Pumpkin",
    "Date": "11082025"
  },
  {
    "Flavor": "Pistachio",
    "Date": "11092025"
  },
  {
    "Flavor": "Chocolate Malt",
    "Date": "11102025"
  },
  {
    "Flavor": "Cinnamon Bun",
    "Date": "11112025"
  },
  {
    "Flavor": "Strawberry",
    "Date": "11122025"
  },
  {
    "Flavor": "Pumpkin",
    "Date": "11132025"
  },
  {
    "Flavor": "Peanut Butter",
    "Date": "11142025"
  },
  {
    "Flavor": "Caramel Apple Crunch",
    "Date": "11152025"
  },
  {
    "Flavor": "Peppermint",
    "Date": "11162025"
  },
  {
    "Flavor": "Salted Caramel",
    "Date": "11172025"
  },
  {
    "Flavor": "Burgundy Cherry",
    "Date": "11182025"
  },
  {
    "Flavor": "Butter Pecan",
    "Date": "11192025"
  },
  {
    "Flavor": "Jamocha",
    "Date": "11202025"
  },
  {
    "Flavor": "Pumpkin",
    "Date": "11212025"
  },
  {
    "Flavor": "Chocolate Chip Cookie Dough",
    "Date": "11222025"
  },
  {
    "Flavor": "Mint Chocolate Chip",
    "Date": "11232025"
  },
  {
    "Flavor": "Chai Latte Chocolate Chip",
    "Date": "11242025"
  },
  {
    "Flavor": "Pistachio",
    "Date": "11252025"
  },
  {
    "Flavor": "Pumpkin",
    "Date": "11262025"
  },
  {
    "Flavor": "CLOSED",
    "Date": "11272025"
  },
  {
    "Flavor": "Peppermint",
    "Date": "11282025"
  },
  {
    "Flavor": "Strawberry",
    "Date": "11292025"
  },
  {
    "Flavor": "Cinnamon Bun",
    "Date": "11302025"
  }
]
